SqliteXuexiShouce/README.md
SqliteXuexiShouce/__init__.py
SqliteXuexiShouce/__main__.py
SqliteXuexiShouce/file.epub
SqliteXuexiShouce/index.html
SqliteXuexiShouce/css/__init__.py
SqliteXuexiShouce/css/annotations.css
SqliteXuexiShouce/css/main.css
SqliteXuexiShouce/css/normalize.css
SqliteXuexiShouce/css/popup.css
SqliteXuexiShouce/font/__init__.py
SqliteXuexiShouce/font/fontello.eot
SqliteXuexiShouce/font/fontello.svg
SqliteXuexiShouce/font/fontello.ttf
SqliteXuexiShouce/font/fontello.woff
SqliteXuexiShouce/img/__init__.py
SqliteXuexiShouce/img/annotator-glyph-sprite.png
SqliteXuexiShouce/img/annotator-icon-sprite.png
SqliteXuexiShouce/img/apple-touch-icon.png
SqliteXuexiShouce/img/cancelfullscreen.png
SqliteXuexiShouce/img/close.png
SqliteXuexiShouce/img/fullscreen.png
SqliteXuexiShouce/img/loader.gif
SqliteXuexiShouce/img/menu-icon.png
SqliteXuexiShouce/img/save.png
SqliteXuexiShouce/img/saved.png
SqliteXuexiShouce/img/settings-s.png
SqliteXuexiShouce/img/settings.png
SqliteXuexiShouce/img/star.png
SqliteXuexiShouce/js/__init__.py
SqliteXuexiShouce/js/epub.js
SqliteXuexiShouce/js/epub.min.js
SqliteXuexiShouce/js/epub.min.map
SqliteXuexiShouce/js/hooks.min.js
SqliteXuexiShouce/js/hooks.min.map
SqliteXuexiShouce/js/reader.js
SqliteXuexiShouce/js/reader.js.map
SqliteXuexiShouce/js/reader.min.js
SqliteXuexiShouce/js/reader.min.map
SqliteXuexiShouce/js/hooks/__init__.py
SqliteXuexiShouce/js/hooks/extensions/__init__.py
SqliteXuexiShouce/js/hooks/extensions/highlight.js
SqliteXuexiShouce/js/libs/__init__.py
SqliteXuexiShouce/js/libs/jquery.min.js
SqliteXuexiShouce/js/libs/localforage.min.js
SqliteXuexiShouce/js/libs/screenfull.js
SqliteXuexiShouce/js/libs/screenfull.min.js
SqliteXuexiShouce/js/libs/zip.min.js
SqliteXuexiShouce/js/plugins/__init__.py
SqliteXuexiShouce/js/plugins/hypothesis.js
SqliteXuexiShouce/js/plugins/search.js
sqlite_xuexi_shouce-2024.3.2.0.dist-info/METADATA
sqlite_xuexi_shouce-2024.3.2.0.dist-info/WHEEL
sqlite_xuexi_shouce-2024.3.2.0.dist-info/entry_points.txt
sqlite_xuexi_shouce-2024.3.2.0.dist-info/top_level.txt
sqlite_xuexi_shouce-2024.3.2.0.dist-info/RECORD
